{
 "updated": "2026-06-22T13:36:36+00:00",
 "edge": {
  "w": 80,
  "l": 56,
  "pending": 0,
  "pct": 0.588,
  "brier": 0.2436
 },
 "all": {
  "w": 350,
  "l": 293,
  "pending": 13,
  "pct": 0.544,
  "brier": 0.2487
 },
 "tiers": [
  {
   "band": "0.500-0.550",
   "n": 338,
   "w": 186,
   "l": 152,
   "pct": 0.55,
   "edge": false
  },
  {
   "band": "0.550-0.575",
   "n": 157,
   "w": 76,
   "l": 81,
   "pct": 0.484,
   "edge": false
  },
  {
   "band": "0.575-0.600",
   "n": 67,
   "w": 37,
   "l": 30,
   "pct": 0.552,
   "edge": true
  },
  {
   "band": "0.600-0.650",
   "n": 68,
   "w": 44,
   "l": 24,
   "pct": 0.647,
   "edge": true
  },
  {
   "band": "0.650+",
   "n": 13,
   "w": 7,
   "l": 6,
   "pct": 0.538,
   "edge": true
  }
 ],
 "by_date": [
  {
   "date": "2026-06-22",
   "edge_w": 0,
   "edge_l": 0,
   "all_w": 0,
   "all_l": 0
  },
  {
   "date": "2026-06-21",
   "edge_w": 1,
   "edge_l": 2,
   "all_w": 8,
   "all_l": 6
  },
  {
   "date": "2026-06-20",
   "edge_w": 0,
   "edge_l": 3,
   "all_w": 4,
   "all_l": 10
  },
  {
   "date": "2026-06-16",
   "edge_w": 2,
   "edge_l": 2,
   "all_w": 8,
   "all_l": 7
  },
  {
   "date": "2026-06-14",
   "edge_w": 2,
   "edge_l": 0,
   "all_w": 5,
   "all_l": 9
  },
  {
   "date": "2026-06-13",
   "edge_w": 2,
   "edge_l": 1,
   "all_w": 10,
   "all_l": 5
  },
  {
   "date": "2026-06-12",
   "edge_w": 1,
   "edge_l": 0,
   "all_w": 6,
   "all_l": 9
  },
  {
   "date": "2026-06-11",
   "edge_w": 1,
   "edge_l": 0,
   "all_w": 6,
   "all_l": 1
  },
  {
   "date": "2026-06-10",
   "edge_w": 1,
   "edge_l": 0,
   "all_w": 5,
   "all_l": 10
  },
  {
   "date": "2026-06-09",
   "edge_w": 0,
   "edge_l": 0,
   "all_w": 9,
   "all_l": 6
  },
  {
   "date": "2026-06-08",
   "edge_w": 1,
   "edge_l": 0,
   "all_w": 6,
   "all_l": 2
  },
  {
   "date": "2026-06-07",
   "edge_w": 3,
   "edge_l": 1,
   "all_w": 9,
   "all_l": 6
  },
  {
   "date": "2026-06-06",
   "edge_w": 3,
   "edge_l": 0,
   "all_w": 10,
   "all_l": 4
  },
  {
   "date": "2026-06-05",
   "edge_w": 3,
   "edge_l": 1,
   "all_w": 8,
   "all_l": 7
  },
  {
   "date": "2026-06-04",
   "edge_w": 1,
   "edge_l": 2,
   "all_w": 4,
   "all_l": 5
  },
  {
   "date": "2026-06-03",
   "edge_w": 1,
   "edge_l": 3,
   "all_w": 5,
   "all_l": 10
  },
  {
   "date": "2026-06-02",
   "edge_w": 2,
   "edge_l": 2,
   "all_w": 8,
   "all_l": 7
  },
  {
   "date": "2026-06-01",
   "edge_w": 1,
   "edge_l": 1,
   "all_w": 3,
   "all_l": 6
  },
  {
   "date": "2026-05-31",
   "edge_w": 3,
   "edge_l": 1,
   "all_w": 11,
   "all_l": 4
  },
  {
   "date": "2026-05-30",
   "edge_w": 1,
   "edge_l": 2,
   "all_w": 9,
   "all_l": 6
  },
  {
   "date": "2026-05-29",
   "edge_w": 2,
   "edge_l": 0,
   "all_w": 12,
   "all_l": 3
  }
 ]
}